_env/Lib/site-packages/_virtualenv.py
_env/Lib/site-packages/_distutils_hack/__init__.py
_env/Lib/site-packages/_distutils_hack/override.py
_env/Lib/site-packages/build/__init__.py
_env/Lib/site-packages/build/__main__.py
_env/Lib/site-packages/build/_exceptions.py
_env/Lib/site-packages/build/_importlib.py
_env/Lib/site-packages/build/_util.py
_env/Lib/site-packages/build/env.py
_env/Lib/site-packages/build/util.py
_env/Lib/site-packages/certifi/__init__.py
_env/Lib/site-packages/certifi/__main__.py
_env/Lib/site-packages/certifi/core.py
_env/Lib/site-packages/charset_normalizer/__init__.py
_env/Lib/site-packages/charset_normalizer/api.py
_env/Lib/site-packages/charset_normalizer/cd.py
_env/Lib/site-packages/charset_normalizer/constant.py
_env/Lib/site-packages/charset_normalizer/legacy.py
_env/Lib/site-packages/charset_normalizer/md.py
_env/Lib/site-packages/charset_normalizer/models.py
_env/Lib/site-packages/charset_normalizer/utils.py
_env/Lib/site-packages/charset_normalizer/version.py
_env/Lib/site-packages/charset_normalizer/assets/__init__.py
_env/Lib/site-packages/charset_normalizer/cli/__init__.py
_env/Lib/site-packages/charset_normalizer/cli/normalizer.py
_env/Lib/site-packages/colorama/__init__.py
_env/Lib/site-packages/colorama/ansi.py
_env/Lib/site-packages/colorama/ansitowin32.py
_env/Lib/site-packages/colorama/initialise.py
_env/Lib/site-packages/colorama/win32.py
_env/Lib/site-packages/colorama/winterm.py
_env/Lib/site-packages/docutils/__init__.py
_env/Lib/site-packages/docutils/__main__.py
_env/Lib/site-packages/docutils/core.py
_env/Lib/site-packages/docutils/examples.py
_env/Lib/site-packages/docutils/frontend.py
_env/Lib/site-packages/docutils/io.py
_env/Lib/site-packages/docutils/nodes.py
_env/Lib/site-packages/docutils/statemachine.py
_env/Lib/site-packages/docutils/languages/__init__.py
_env/Lib/site-packages/docutils/languages/af.py
_env/Lib/site-packages/docutils/languages/ar.py
_env/Lib/site-packages/docutils/languages/ca.py
bg3modutils_fierrof-0.0.1.dist-info/METADATA
bg3modutils_fierrof-0.0.1.dist-info/WHEEL
bg3modutils_fierrof-0.0.1.dist-info/licenses/LICENCE
bg3modutils_fierrof-0.0.1.dist-info/RECORD
